{
    "appKeys": {},
    "capabilities": [
        ""
    ],
    "companyName": "malcolm.anteros@gmail.com",
    "longName": "tertiary_text",
    "projectType": "pebblejs",
    "resources": {
        "media": [
            {
                "file": "images/menu_icon.png",
                "menuIcon": true,
                "name": "IMAGE_MENU_ICON",
                "type": "bitmap"
            },
            {
                "file": "images/logo_splash.png",
                "name": "IMAGE_LOGO_SPLASH",
                "type": "bitmap"
            },
            {
                "file": "images/abcdefghi.png",
                "name": "ABCDEFGHI",
                "type": "bitmap"
            },
            {
                "file": "fonts/UbuntuMono-Regular.ttf",
                "name": "MONO_FONT_14",
                "type": "font"
            }
        ]
    },
    "sdkVersion": "3",
    "shortName": "tertiary_text",
    "targetPlatforms": [
        "aplite",
        "basalt"
    ],
    "uuid": "2753a806-9a07-4a8e-b218-2127d14bb923",
    "versionCode": 1,
    "versionLabel": "1.0",
    "watchapp": {
        "hiddenApp": false,
        "watchface": false
    }
}
